Metadata-Version: 2.1
Name: var-distributions
Version: 0.2
Summary: Gaussian and Binomial Discription
Home-page: UNKNOWN
Author: Apaar Bawa
License: UNKNOWN
Platform: UNKNOWN
